CHANGES
LICENSE
README.txt
setup.py
iw/__init__.py
iw.sql.egg-info/PKG-INFO
iw.sql.egg-info/SOURCES.txt
iw.sql.egg-info/dependency_links.txt
iw.sql.egg-info/entry_points.txt
iw.sql.egg-info/namespace_packages.txt
iw.sql.egg-info/not-zip-safe
iw.sql.egg-info/requires.txt
iw.sql.egg-info/top_level.txt
iw/sql/README.txt
iw/sql/__init__.py
iw/sql/wrapper.py
iw/sql/docs/README.txt
iw/sql/doctests/README.txt
iw/sql/doctests/wrapper.txt
iw/sql/tests/__init__.py
iw/sql/tests/test_sqlalchemydocs.py
iw/sql/tests/test_wrapper.py
