Metadata-Version: 1.0
Name: iw.sql
Version: 0.1
Summary: Package on the top of z3c.sqlalchemy to provide automatic retries
Home-page: UNKNOWN
Author: Ingeniweb
Author-email: support@ingeniweb.com
License: GPL
Keywords: sql sql zope
Platform: UNKNOWN
Classifier: Programming Language :: Python
Classifier: Topic :: Software Development :: Libraries :: Python Modules
